odoo/addons/url_attachment_search_fuzzy/README.rst
odoo/addons/url_attachment_search_fuzzy/__init__.py
odoo/addons/url_attachment_search_fuzzy/__manifest__.py
odoo/addons/url_attachment_search_fuzzy/data/url_attachment_index.xml
odoo/addons/url_attachment_search_fuzzy/i18n/url_attachment_search_fuzzy.pot
odoo/addons/url_attachment_search_fuzzy/readme/CONFIGURE.rst
odoo/addons/url_attachment_search_fuzzy/readme/CONTRIBUTORS.rst
odoo/addons/url_attachment_search_fuzzy/readme/DESCRIPTION.rst
odoo/addons/url_attachment_search_fuzzy/readme/INSTALL.rst
odoo/addons/url_attachment_search_fuzzy/static/description/icon.png
odoo/addons/url_attachment_search_fuzzy/static/description/index.html
odoo14_addon_url_attachment_search_fuzzy-14.0.1.0.1.dist-info/METADATA
odoo14_addon_url_attachment_search_fuzzy-14.0.1.0.1.dist-info/WHEEL
odoo14_addon_url_attachment_search_fuzzy-14.0.1.0.1.dist-info/top_level.txt
odoo14_addon_url_attachment_search_fuzzy-14.0.1.0.1.dist-info/RECORD
